serializers/__init__.py
serializers/factory.py
serializers/base/__init__.py
serializers/base/constants.py
serializers/base/deserialization.py
serializers/base/serialization.py
serializers/json_serializer/JsonSerializer.py
serializers/json_serializer/__init__.py
serializers/json_serializer/serialization_logic.py
serializers/xml_serializer/XmlSerializer.py
serializers/xml_serializer/__init__.py
serializers/xml_serializer/serialization_logic.py
Shchirov_s_serializer-1.0.0.dist-info/METADATA
Shchirov_s_serializer-1.0.0.dist-info/WHEEL
Shchirov_s_serializer-1.0.0.dist-info/top_level.txt
Shchirov_s_serializer-1.0.0.dist-info/RECORD
